Modulos/FIFO/Counter.v

`timescale 1ns/1ps

module counter();

  reg clk;
  reg push;
  reg pop;
  reg reset;
  reg [3:0] contadorW;
  reg [3:0] contadorR;
  reg vueltaR;
  reg vueltaW;


  always @ (posedge clk) begin
    if (push) begin
      if (contadorW == 7) begin
        contadorW <= 0;
        vueltaW <= vueltaW == 1 ? 0 : 1;
      end else begin
        contadorW <= contadorW+4'b0001;
      end
      // contadorW <= contadorW == 4'b0111 ? 0 : contadorW+4'b0001;
    end

    if (pop) begin
      if (contadorR == 7) begin
        contadorR <= 0;
        vueltaR <= vueltaR == 1 ? 0 : 1;
      end else begin
        contadorR <= contadorR+4'b0001;
      end
      //contadorR <= contadorR == 7 ? 0 : contadorR+1;
    end
  end

  always # 4 clk = ~clk;

  initial begin
    $dumpfile("gtkws/testCounter.vcd");
    $dumpvars;
  end

  initial begin

    contadorR<= 4'b0000;
    contadorW<= 4'b0000;
    clk<= 0;
    push<= 1;
    pop<= 0;
    reset<= 0;
    vueltaR<= 0;
    vueltaW<= 0;

    # 4
    @ (posedge clk);



    # 4
    @ (posedge clk);


    # 4
    @ (posedge clk);

    # 4
    @ (posedge clk);

    # 4
    @ (posedge clk);

    # 4
    @ (posedge clk);

    $finish;
  end



endmodule

Modulos/FIFO/gtkws/testCounter.vcd
$date
	Sat Jun 30 15:45:02 2018
$end
$version
	Icarus Verilog
$end
$timescale
	1ps
$end
$scope module counter $end
$var reg 1 ! clk $end
$var reg 4 " contadorR [3:0] $end
$var reg 4 # contadorW [3:0] $end
$var reg 1 $ pop $end
$var reg 1 % push $end
$var reg 1 & reset $end
$var reg 1 ' vueltaR $end
$var reg 1 ( vueltaW $end
$upscope $end
$enddefinitions $end
#0
$dumpvars
0(
0'
0&
1%
0$
b0 #
b0 "
0!
$end
#4000
b1 #
1!
#8000
0!
#12000
b10 #
1!
#16000
0!
#20000
b11 #
1!
#24000
0!
#28000
b100 #
1!
#32000
0!
#36000
b101 #
1!
#40000
0!
#44000
b110 #
1!
#48000
0!
#52000
b111 #
1!
