Modulos/FIFO/DRAM1.v
module DRAM1
(
	input [3:0] data_a,
	input [3:0] addr_a, addr_b,
	input we_a, re_b, clk,
	output reg [3:0] q_b
);

	//parameter f = 3, c = 7;
	// Declare the RAM variable
	//reg [f:0] ram[c];
	reg [3:0] ram[7:0];

	// Port A
	always @ (posedge clk)
	begin
		if (we_a)
		begin
			ram[addr_a] <= data_a;
		end

	end

	// Port B
	always @ (posedge clk)
	begin
		if (re_b)
		begin
			q_b <= ram[addr_b];
		end

	end
endmodule

Modulos/FIFO/FIFO.v
`include "DRAM/DRAM1.v"


module FIFO
(
	input [3:0] data_a,
	input clk, push, pop, reset,
	output wire [3:0] q_b,
  output reg error, full, empty, almost_full, almost_empty
);

	reg [3:0] contadorR;
	reg [3:0] contadorW;
	reg vueltaR;
	reg vueltaW;

	DRAM1 ram(.data_a(data_a), .addr_a(contadorW), .addr_b(contadorR), .we_a(push), .re_b(pop), .clk(clk), .q_b(q_b));


	always @ (posedge clk) begin
		if (reset == 1) begin
			contadorR <= 4'b0000;
			vueltaR <= 0;
			empty <= 1;
			full <= 0;
			almost_full <= 0;
			almost_empty <= 0;
			error <= 0;
			contadorW <= 4'b0000;
			vueltaW <= 0;
		end else begin
			if(contadorR==contadorW) begin
				if(vueltaR==vueltaW) begin
					empty <= 1;
					full <= 0;
					almost_full <= 0;
					almost_empty <= 0;
					error <= 0;
				end else begin
					empty <= 0;
					full <= 1;
					almost_full <= 0;
					almost_empty <= 0;
					error <= 0;
				end
			end else if(contadorR>contadorW)begin
				if(vueltaR==vueltaW) begin
					empty <= 0;
					full <= 0;
					almost_full <= 0;
					almost_empty <= 0;
					error <= 1;
				end else begin
					empty <= 0;
					full <= 0;
					error <= 0;
					if (contadorW + 8 - contadorR<=1) begin
						almost_empty <= 1;
						almost_full <= 0;
					end else if (contadorW + 8 - contadorR >= 6) begin
						almost_empty <= 0;
						almost_full <= 1;
					end else begin
						almost_empty <= 0;
						almost_full <= 0;
					end
				end
			end else begin
				if(vueltaR==vueltaW) begin
					empty <= 0;
					full <= 0;
					error <= 0;
					if (contadorW - contadorR<=1) begin
						almost_empty <= 1;
						almost_full <= 0;
					end else if (contadorW - contadorR >= 6) begin
						almost_empty <= 0;
						almost_full <= 1;
					end else begin
						almost_empty <= 0;
						almost_full <= 0;
					end
				end else begin
					empty <= 0;
					full <= 0;
					almost_full <= 0;
					almost_empty <= 0;
					error <= 1;
				end
			end
		end
	end


	always @ (posedge clk) begin
		if (push) begin
			if (contadorW == 7) begin
				contadorW <= 0;
				vueltaW <= vueltaW == 1 ? 0 : 1;
			end else begin
				contadorW <= contadorW+4'b0001;
			end
			// contadorW <= contadorW == 4'b0111 ? 0 : contadorW+4'b0001;
		end

		if (pop) begin
			if (contadorR == 7) begin
				contadorR <= 0;
				vueltaR <= vueltaR == 1 ? 0 : 1;
			end else begin
				contadorR <= contadorR+4'b0001;
			end
			//contadorR <= contadorR == 7 ? 0 : contadorR+1;
		end
	end





endmodule

Modulos/FIFO/TBFifo.v
`timescale 1ns/1ps

`include "FIFO.v"

  module testFIFO ();
  reg [3:0] data_a;
  reg clk;
  reg push;
  reg pop;
  reg reset;
  wire [3:0] q_b;
  wire error;
  wire full;
  wire empty;
  wire almost_full;
  wire almost_empty;

  FIFO fifo(.data_a(data_a), .clk(clk), .push(push), .pop(pop), .reset(reset), .q_b(q_b), .error(error), .full(full), .empty(empty), .almost_full(almost_full), .almost_empty(almost_empty));

  always # 4 clk = ~clk;

  initial begin
    $dumpfile("gtkws/testFIFO.vcd");
    $dumpvars;
  end


  initial begin

    data_a<= 4'b0000;
    clk<= 0;
    push<= 0;
    pop<= 0;
    reset<= 1;

    # 4
    @ (posedge clk);

    reset<= 0;
    push<= 1;

    # 4
    @ (posedge clk);

    data_a<= 4'b0001;

    # 4
    @ (posedge clk);


    data_a<= 4'b0010;

    # 4
    @ (posedge clk);

    data_a<= 4'b0011;

    # 4
    @ (posedge clk);

    data_a<= 4'b0100;

    # 4
    @ (posedge clk);
    pop<= 1;
    data_a<= 4'b0101;

    # 4
    @ (posedge clk);

    data_a<= 4'b0110;

    # 4
    @ (posedge clk);

    data_a<= 4'b0111;

    # 4
    @ (posedge clk);
    push <= 0;

    # 4
    @ (posedge clk);

    # 4
    @ (posedge clk);

    # 4
    @ (posedge clk);






    $finish;
  end


endmodule

Modulos/FIFO/gtkws/testFIFO.vcd
$date
	Sat Jun 30 16:35:46 2018
$end
$version
	Icarus Verilog
$end
$timescale
	1ps
$end
$scope module testFIFO $end
$var wire 1 ! almost_empty $end
$var wire 1 " almost_full $end
$var wire 1 # empty $end
$var wire 1 $ error $end
$var wire 1 % full $end
$var wire 4 & q_b [3:0] $end
$var reg 1 ' clk $end
$var reg 4 ( data_a [3:0] $end
$var reg 1 ) pop $end
$var reg 1 * push $end
$var reg 1 + reset $end
$scope module fifo $end
$var wire 1 , clk $end
$var wire 4 - data_a [3:0] $end
$var wire 1 . pop $end
$var wire 1 / push $end
$var wire 4 0 q_b [3:0] $end
$var wire 1 1 reset $end
$var reg 1 2 almost_empty $end
$var reg 1 3 almost_full $end
$var reg 4 4 contadorR [3:0] $end
$var reg 4 5 contadorW [3:0] $end
$var reg 1 6 empty $end
$var reg 1 7 error $end
$var reg 1 8 full $end
$var reg 1 9 vueltaR $end
$var reg 1 : vueltaW $end
$scope module ram $end
$var wire 4 ; addr_a [3:0] $end
$var wire 4 < addr_b [3:0] $end
$var wire 1 , clk $end
$var wire 4 = data_a [3:0] $end
$var wire 1 . re_b $end
$var wire 1 / we_a $end
$var reg 4 > q_b [3:0] $end
$upscope $end
$upscope $end
$upscope $end
$enddefinitions $end
#0
$dumpvars
bx >
b0 =
bx <
bx ;
x:
x9
x8
x7
x6
bx 5
bx 4
x3
x2
11
bx 0
0/
0.
b0 -
0,
1+
0*
0)
b0 (
0'
bx &
x%
x$
x#
x"
x!
$end
#4000
0:
b0 5
b0 ;
07
0$
02
0!
03
0"
08
0%
16
1#
09
b0 4
b0 <
1'
1,
#8000
0'
0,
#12000
1*
1/
0+
01
1'
1,
#16000
0'
0,
#20000
b1 5
b1 ;
b1 (
b1 -
b1 =
1'
1,
#24000
0'
0,
#28000
b10 5
b10 ;
12
1!
06
0#
b10 (
b10 -
b10 =
1'
1,
#32000
0'
0,
#36000
02
0!
b11 5
b11 ;
b11 (
b11 -
b11 =
1'
1,
#40000
0'
0,
#44000
b100 5
b100 ;
b100 (
b100 -
b100 =
1'
1,
#48000
0'
0,
#52000
b101 5
b101 ;
b101 (
b101 -
b101 =
1)
1.
1'
1,
#56000
0'
0,
#60000
b1 4
b1 <
b110 5
b110 ;
b0 >
b0 &
b0 0
b110 (
b110 -
b110 =
1'
1,
#64000
0'
0,
#68000
b1 >
b1 &
b1 0
b10 4
b10 <
b111 5
b111 ;
b111 (
b111 -
b111 =
1'
1,
#72000
0'
0,
#76000
b11 4
b11 <
1:
b0 5
b0 ;
b10 >
b10 &
b10 0
0*
0/
1'
1,
#80000
0'
0,
#84000
b11 >
b11 &
b11 0
b100 4
b100 <
1'
1,
#88000
0'
0,
#92000
b101 4
b101 <
b100 >
b100 &
b100 0
1'
1,
#96000
0'
0,
#100000
b101 >
b101 &
b101 0
b110 4
b110 <
1'
1,
#104000
0'
0,
#108000
b111 4
b111 <
b110 >
b110 &
b110 0
1'
1,
#112000
0'
0,
#116000
b111 >
b111 &
b111 0
12
1!
19
b0 4
b0 <
1'
1,
#120000
0'
0,
#124000
b1 4
b1 <
02
0!
16
1#
b0 >
b0 &
b0 0
1'
1,
#128000
0'
0,
#132000
b1 >
b1 &
b1 0
17
1$
06
0#
b10 4
b10 <
1'
1,
#136000
0'
0,
#140000
b11 4
b11 <
b10 >
b10 &
b10 0
1'
1,
