Modulos/RoundRobin/RoundRobin.v
module RoundRobin
(
  input reset,
  input req0,
  input req1,
  input req2,
  input req3,
  input [1:0] p0,
  input [1:0] p1,
  input [1:0] p2,
  input [1:0] p3,
  input [1:0] p4,
  input [1:0] p5,
  input [1:0] p6,
  input [1:0] p7,
  input [1:0] p8,
  input [1:0] p9,
  input [1:0] p10,
  input [1:0] p11,
  input [1:0] p12,
  input [1:0] p13,
  input [1:0] p14,
  input [1:0] p15,
   
  input clk,
  output reg valid,
  output reg [1:0] out_id

);

wire [1:0] priority[15:0];

assign priority[0] = p0;
assign priority[1] = p1;
assign priority[2] = p2;
assign priority[3] = p3;
assign priority[4] = p4;
assign priority[5] = p5;
assign priority[6] = p6;
assign priority[7] = p7;
assign priority[8] = p8;
assign priority[9] = p9;
assign priority[10] = p10;
assign priority[11] = p11;
assign priority[12] = p12;
assign priority[13] = p13;
assign priority[14] = p14;
assign priority[15] = p15;

reg [3:0] counter;

// assign valid=0;
// assign out_id = 2'b00;
// assign counter =3'b000;

always @ (posedge clk)
begin
  if (reset) begin

    counter <= 0;
    valid <= 0;
    out_id <= 00;
    end else begin
      case (priority[counter])
        2'b00:
              if (req0) begin
                out_id <= 00;
                valid<=1;
              end else begin
                valid<=0;
              end
        2'b01:
              if (req1) begin
                out_id <= 01;
                valid<=1;
              end else begin
                valid<=0;
              end
        2'b10:
              if (req2) begin
                out_id <= 10;
                valid<=1;
              end else begin
                valid<=0;
              end
        2'b11:
              if (req3) begin
                out_id <= 11;
                valid<=1;
              end else begin
                valid<=0;
              end
      endcase
      counter <= counter + 1;
      end


end

endmodule

Modulos/RoundRobin/tbRRobin.v


`include "RoundRobin.v"

module tbRRobin ();

  reg reset;
  reg clk;

  reg req0;
  reg req1;
  reg req2;
  reg req3;

  reg [1:0] p0;
  reg [1:0] p1;
  reg [1:0] p2;
  reg [1:0] p3;
  reg [1:0] p4;
  reg [1:0] p5;
  reg [1:0] p6;
  reg [1:0] p7;
  reg [1:0] p8;
  reg [1:0] p9;
  reg [1:0] p10;
  reg [1:0] p11;
  reg [1:0] p12;
  reg [1:0] p13;
  reg [1:0] p14;
  reg [1:0] p15;


  wire valid;
  wire [1:0] out_id;

  RoundRobin rndRob(.reset(reset), .clk(clk), .req0(req0), .req1(req1), .req2(req2), .req3(req3), .p0(p0), .p1(p1),
            .p2(p2), .p3(p3), .p4(p4), .p5(p5), .p6(p6), .p7(p7), .p8(p8), .p9(p9), .p10(p10), .p11(p11), .p12(p12), .p13(p13),
            .p14(p14), .p15(p15), .valid(valid), .out_id(out_id));

  always #2 clk = !clk;

  initial begin
    $dumpfile("gtkws/testRRobin.vcd");
    $dumpvars;
  end

  initial begin
    reset <= 1;
    clk <= 0;
    p0 <= 2'b00;
    p1 <= 2'b00;
    p2 <= 2'b00;
    p3 <= 2'b11;
    p4 <= 2'b01;
    p5 <= 2'b10;
    p6 <= 2'b01;
    p7 <= 2'b01;
    p8 <= 2'b11;
    p9 <= 2'b01;
    p10 <= 2'b01;
    p11 <= 2'b00;
    p12 <= 2'b10;
    p13 <= 2'b10;
    p14 <= 2'b01;
    p15 <= 2'b00;

    req0 <= 0;
    req1 <= 0;
    req2 <= 1;
    req3 <= 0;

    #2

    reset <= 0;

    #2

    req0 <= 1;
    req1 <= 0;
    req2 <= 0;
    req3 <= 0;
    #16

    req0 <= 0;
    req1 <= 0;
    req2 <= 1;
    req3 <= 1;

    #16





    $finish;

  end


endmodule

Modulos/RoundRobin/gtkws/testRRobin.vcd
$date
	Sat Jun 30 10:52:12 2018
$end
$version
	Icarus Verilog
$end
$timescale
	1s
$end
$scope module tbRRobin $end
$var wire 1 ! valid $end
$var wire 2 " out_id [1:0] $end
$var reg 1 # clk $end
$var reg 2 $ p0 [1:0] $end
$var reg 2 % p1 [1:0] $end
$var reg 2 & p10 [1:0] $end
$var reg 2 ' p11 [1:0] $end
$var reg 2 ( p12 [1:0] $end
$var reg 2 ) p13 [1:0] $end
$var reg 2 * p14 [1:0] $end
$var reg 2 + p15 [1:0] $end
$var reg 2 , p2 [1:0] $end
$var reg 2 - p3 [1:0] $end
$var reg 2 . p4 [1:0] $end
$var reg 2 / p5 [1:0] $end
$var reg 2 0 p6 [1:0] $end
$var reg 2 1 p7 [1:0] $end
$var reg 2 2 p8 [1:0] $end
$var reg 2 3 p9 [1:0] $end
$var reg 1 4 req0 $end
$var reg 1 5 req1 $end
$var reg 1 6 req2 $end
$var reg 1 7 req3 $end
$var reg 1 8 reset $end
$scope module rndRob $end
$var wire 1 # clk $end
$var wire 2 9 p0 [1:0] $end
$var wire 2 : p1 [1:0] $end
$var wire 2 ; p10 [1:0] $end
$var wire 2 < p11 [1:0] $end
$var wire 2 = p12 [1:0] $end
$var wire 2 > p13 [1:0] $end
$var wire 2 ? p14 [1:0] $end
$var wire 2 @ p15 [1:0] $end
$var wire 2 A p2 [1:0] $end
$var wire 2 B p3 [1:0] $end
$var wire 2 C p4 [1:0] $end
$var wire 2 D p5 [1:0] $end
$var wire 2 E p6 [1:0] $end
$var wire 2 F p7 [1:0] $end
$var wire 2 G p8 [1:0] $end
$var wire 2 H p9 [1:0] $end
$var wire 1 4 req0 $end
$var wire 1 5 req1 $end
$var wire 1 6 req2 $end
$var wire 1 7 req3 $end
$var wire 1 8 reset $end
$var reg 4 I counter [3:0] $end
$var reg 2 J out_id [1:0] $end
$var reg 1 ! valid $end
$upscope $end
$upscope $end
$enddefinitions $end
#0
$dumpvars
bx J
bx I
b1 H
b11 G
b1 F
b1 E
b10 D
b1 C
b11 B
b0 A
b0 @
b1 ?
b10 >
b10 =
b0 <
b1 ;
b0 :
b0 9
18
07
16
05
04
b1 3
b11 2
b1 1
b1 0
b10 /
b1 .
b11 -
b0 ,
b0 +
b1 *
b10 )
b10 (
b0 '
b1 &
b0 %
b0 $
0#
bx "
x!
$end
#2
b0 "
b0 J
0!
b0 I
08
1#
#4
06
14
0#
#6
b1 I
1!
1#
#8
0#
#10
b10 I
1#
#12
0#
#14
b11 I
1#
#16
0#
#18
b100 I
0!
1#
#20
17
16
04
0#
#22
b101 I
1#
#24
0#
#26
b110 I
1!
b10 "
b10 J
1#
#28
0#
#30
b111 I
0!
1#
#32
0#
#34
b1000 I
1#
